pystc/__init__.py
pystc/pystc.py
pystc-2.0.0.dist-info/LICENSE
pystc-2.0.0.dist-info/METADATA
pystc-2.0.0.dist-info/WHEEL
pystc-2.0.0.dist-info/RECORD
